DataPrepKitt
