Metadata-Version: 2.1
Name: DataPrepKitt
Version: 0.0.3
Summary: This package aims to be a comprehensive toolkit for preprocessing datasets.
Author: Manar Yabrak
Author-email: manar.mofid@gmail.com
Classifier: Programming Language :: Python :: 3
Classifier: License :: OSI Approved :: MIT License
Classifier: Operating System :: OS Independent
Requires-Python: >=3.6
Requires-Dist: numpy==1.21.4
Requires-Dist: pandas==1.3.4
Requires-Dist: openpyxl==3.1.2
